README.md
setup.py
weixin/__init__.py
weixin/base.py
weixin/login.py
weixin/mp.py
weixin/msg.py
weixin/pay.py
weixin_python.egg-info/PKG-INFO
weixin_python.egg-info/SOURCES.txt
weixin_python.egg-info/dependency_links.txt
weixin_python.egg-info/not-zip-safe
weixin_python.egg-info/requires.txt
weixin_python.egg-info/top_level.txt