Metadata-Version: 1.0
Name: weixin-python
Version: 0.5.3
Summary: Weixin for Python
Home-page: https://github.com/zwczou/weixin-python
Author: zwczou
Author-email: zwczou@gmail.com
License: BSD
Keywords: weixin,weixin pay,weixin login
Platform: any
